supermind/VERSION.txt
supermind/__init__.py
supermind/__main__.py
supermind/mod_config.yml
supermind/api/__init__.py
supermind/data/__init__.py
supermind/data/main.cpython-38-darwin.so
supermind/mod/__init__.py
supermind/mod/analyser/__init__.py
supermind/mod/analyser/mod.cpython-38-darwin.so
supermind/mod/analyser/plot.cpython-38-darwin.so
supermind/mod/analyser/report.cpython-38-darwin.so
supermind/mod/analyser/research_api.cpython-38-darwin.so
supermind/mod/mindgo/__init__.py
supermind/mod/mindgo/errors.cpython-38-darwin.so
supermind/mod/mindgo/event_func.cpython-38-darwin.so
supermind/mod/mindgo/kafka_output.cpython-38-darwin.so
supermind/mod/mindgo/mod.cpython-38-darwin.so
supermind/mod/mindgo/service.cpython-38-darwin.so
supermind/mod/mindgo/setting.cpython-38-darwin.so
supermind/mod/mindgo/simulate.cpython-38-darwin.so
supermind/mod/mindgo/api/__init__.py
supermind/mod/mindgo/api/api_comm.cpython-38-darwin.so
supermind/mod/mindgo/data/__init__.py
supermind/mod/mindgo/data/_calendar_adapter.cpython-38-darwin.so
supermind/mod/mindgo/data/_calendar_bisect.cpython-38-darwin.so
supermind/mod/mindgo/data/_calendar_helpers.cpython-38-darwin.so
supermind/mod/mindgo/data/bar_bcolz_store.cpython-38-darwin.so
supermind/mod/mindgo/data/extra_bcolz_store.cpython-38-darwin.so
supermind/mod/mindgo/data/extra_hdf_store.cpython-38-darwin.so
supermind/mod/mindgo/data/instrument_store.cpython-38-darwin.so
supermind/mod/mindgo/data/trading_dates_store.cpython-38-darwin.so
supermind/mod/mindgo/modules/__init__.py
supermind/mod/mindgo/modules/hxcelery_utils/PortfolioMeasure.cpython-38-darwin.so
supermind/mod/mindgo/modules/hxcelery_utils/PortfolioMeasureMG.cpython-38-darwin.so
supermind/mod/mindgo/modules/hxcelery_utils/__init__.py
supermind/mod/mindgo/modules/hxcelery_utils/calendar_util.cpython-38-darwin.so
supermind/mod/mindgo/modules/hxcelery_utils/hxpaper.cpython-38-darwin.so
supermind/mod/mindgo/modules/hxcelery_utils/portfolio_util.cpython-38-darwin.so
supermind-0.3.1.dist-info/METADATA
supermind-0.3.1.dist-info/WHEEL
supermind-0.3.1.dist-info/entry_points.txt
supermind-0.3.1.dist-info/top_level.txt
supermind-0.3.1.dist-info/RECORD
